mememo/__init__.py
mememo/main.py
mememo-1.1.dist-info/METADATA
mememo-1.1.dist-info/WHEEL
mememo-1.1.dist-info/top_level.txt
mememo-1.1.dist-info/RECORD
