Metadata-Version: 2.4
Name: mememo
Version: 1.1
Summary: Lightweight package to find the mean, median, and mode.
Author: dUhEnC-39
Classifier: Programming Language :: Python :: 3
Classifier: License :: OSI Approved :: MIT License
Classifier: Operating System :: OS Independent
Requires-Python: >=2.5
Dynamic: author
Dynamic: classifier
Dynamic: description
Dynamic: description-content-type
Dynamic: requires-python
Dynamic: summary
